LICENSE
MANIFEST.in
README.md
pyproject.toml
setup.py
src/zxy9_biomechanical_model/__init__.py
src/zxy9_biomechanical_model/sim_c_util.c
src/zxy9_biomechanical_model/simulation.py
src/zxy9_biomechanical_model.egg-info/PKG-INFO
src/zxy9_biomechanical_model.egg-info/SOURCES.txt
src/zxy9_biomechanical_model.egg-info/dependency_links.txt
src/zxy9_biomechanical_model.egg-info/requires.txt
src/zxy9_biomechanical_model.egg-info/top_level.txt
src/zxy9_biomechanical_model/sim_c_helper/Sim_Entry_Object.c
src/zxy9_biomechanical_model/sim_c_helper/Sim_Entry_Type.c
src/zxy9_biomechanical_model/sim_c_helper/math_helper.c
src/zxy9_biomechanical_model/sim_c_helper/numpy_helper.c
src/zxy9_biomechanical_model/sim_py_util/__init__.py
src/zxy9_biomechanical_model/sim_py_util/body.py
src/zxy9_biomechanical_model/sim_py_util/json_util.py