Metadata-Version: 2.4
Name: zxy9_biomechanical_model
Version: 0.0.7
Summary: A 2d biomechanical model of human motion. Or, the motion of some other kind of animal / robot / thing, if its motion is close enough to 2d and you can find the parameter values for it.
Author-email: Sam Liepke <samliepke@gmail.com>
License-File: LICENSE
Requires-Dist: numpy
Requires-Dist: gymnasium
Dynamic: license-file
